mbtav3/__init__.py
mbtav3/auth.py
mbtav3/const.py
mbtav3/mbta.py
mbtav3/test_predictions.py
mbtav3/utils.py
mbtav3-0.3.dist-info/LICENSE
mbtav3-0.3.dist-info/METADATA
mbtav3-0.3.dist-info/WHEEL
mbtav3-0.3.dist-info/top_level.txt
mbtav3-0.3.dist-info/RECORD
