Metadata-Version: 2.1
Name: mbtav3
Version: 0.3
Summary: Python library for MBTA v3 realtime API
Home-page: https://github.com/djsv23/mbtav3
Author: Daniel Steiner
Author-email: djsteiner93@gmail.com
License: MIT
Platform: UNKNOWN
Classifier: Intended Audience :: Developers
Classifier: Development Status :: 3 - Alpha
Classifier: License :: OSI Approved :: MIT License
Classifier: Programming Language :: Python :: 3
Classifier: Programming Language :: Python :: 3 :: Only
Classifier: Topic :: Internet :: WWW/HTTP
Classifier: Topic :: Software Development :: Libraries
Requires-Dist: aiohttp
